config/__init__.py
config/asgi.py
config/settings.py
config/urls.py
config/wsgi.py
mikoa/__init__.py
mikoa/apps.py
mikoa/mikoa.csv
mikoa/models.py
mikoa/tests.py
mikoa/urls.py
mikoa/wilaya.csv
mikoa/migrations/0001_initial.py
mikoa/migrations/0002_auto_20210523_1414.py
mikoa/migrations/__init__.py
django_mikoa-0.0.3.dist-info/LICENSE
django_mikoa-0.0.3.dist-info/METADATA
django_mikoa-0.0.3.dist-info/WHEEL
django_mikoa-0.0.3.dist-info/top_level.txt
django_mikoa-0.0.3.dist-info/RECORD
