Metadata-Version: 2.1
Name: django-mikoa
Version: 0.0.3
Summary: Django app for Tanzania Regions and Districts
Home-page: https://github.com/devmed/django-mikoa
Author: Medson Naftali
Author-email: medsonnaftal@gmail.com
License: UNKNOWN
Project-URL: Bug Tracker, https://github.com/devmed/django-mikoa/issues
Platform: UNKNOWN
Classifier: Programming Language :: Python :: 3
Classifier: License :: OSI Approved :: MIT License
Classifier: Operating System :: OS Independent
License-File: LICENSE
